flask_restful_url_generator/__init__.py
flask_restful_url_generator/urls.py
flask_restful_url_generator-0.0.4.dist-info/DESCRIPTION.rst
flask_restful_url_generator-0.0.4.dist-info/METADATA
flask_restful_url_generator-0.0.4.dist-info/RECORD
flask_restful_url_generator-0.0.4.dist-info/WHEEL
flask_restful_url_generator-0.0.4.dist-info/metadata.json
flask_restful_url_generator-0.0.4.dist-info/top_level.txt
