Metadata-Version: 1.1
Name: flask_restful_url_generator
Version: 0.0.4
Summary: flask-restful URLs list
Home-page: https://github.com/ojarva/flask-restful-url-generator
Author: Olli Jarva
Author-email: olli@jarva.fi
License: BSD
Keywords: flask restful
Platform: UNKNOWN
Classifier: Development Status :: 4 - Beta
Classifier: Intended Audience :: Developers
Classifier: Intended Audience :: System Administrators
Classifier: License :: OSI Approved :: BSD License
Classifier: Programming Language :: Python :: 2.6
Classifier: Programming Language :: Python :: 2.7
Classifier: Programming Language :: Python :: 3
Classifier: Programming Language :: Python :: 3.2
Classifier: Programming Language :: Python :: 3.3
Classifier: Programming Language :: Python :: 3.4
Classifier: Programming Language :: Python :: Implementation :: PyPy
